stereo_map_tools/_C_stereo_map_tools.cpython-38-darwin.so
stereo_map_tools/_C_stereo_map_tools.pyi
stereo_map_tools/__init__.py
stereo_map_tools/_internal.cpython-38-darwin.so
stereo_map_tools/utils.py
stereo_map_tools/version.py
stereo_map_tools-20250626a1.dist-info/METADATA
stereo_map_tools-20250626a1.dist-info/WHEEL
stereo_map_tools-20250626a1.dist-info/top_level.txt
stereo_map_tools-20250626a1.dist-info/RECORD
